polybot/__init__.py
polybot/bot.py
polybot/image.py
polybot/service.py
polybot-0.9.7.dist-info/licenses/LICENSE
polybot-0.9.7.dist-info/METADATA
polybot-0.9.7.dist-info/WHEEL
polybot-0.9.7.dist-info/top_level.txt
polybot-0.9.7.dist-info/RECORD
