Metadata-Version: 2.4
Name: polybot
Version: 0.9.7
Summary: A simple framework for building robust social media bots for multiple networks
Author-email: Russ Garrett <russ@garrett.co.uk>
Project-URL: Homepage, https://github.com/russss/polybot
Classifier: Development Status :: 4 - Beta
Classifier: License :: OSI Approved :: MIT License
Classifier: Programming Language :: Python :: 3
Requires-Python: <3.13,>=3.9
License-File: LICENSE
Requires-Dist: atproto>=0.0.56
Requires-Dist: httpx>=0.27.2
Requires-Dist: mastodon-py>=1.8.1
Requires-Dist: pillow>=11.0.0
Requires-Dist: tweepy>=4.14.0
Dynamic: license-file
